rest_framework_swagger/__init__.py
rest_framework_swagger/renderers.py
rest_framework_swagger/settings.py
rest_framework_swagger/views.py
rest_framework_swagger/static/rest_framework_swagger/favicon-16x16.png
rest_framework_swagger/static/rest_framework_swagger/favicon-32x32.png
rest_framework_swagger/static/rest_framework_swagger/logo_small.png
rest_framework_swagger/static/rest_framework_swagger/bundles/app.bundle.css
rest_framework_swagger/static/rest_framework_swagger/bundles/app.bundle.js
rest_framework_swagger/static/rest_framework_swagger/bundles/vendors.bundle.css
rest_framework_swagger/static/rest_framework_swagger/bundles/vendors.bundle.js
rest_framework_swagger/static/rest_framework_swagger/css/custom-css.css
rest_framework_swagger/templates/rest_framework_swagger/index.html
mma_django_rest_swagger-2.2.1.dist-info/LICENSE
mma_django_rest_swagger-2.2.1.dist-info/METADATA
mma_django_rest_swagger-2.2.1.dist-info/WHEEL
mma_django_rest_swagger-2.2.1.dist-info/top_level.txt
mma_django_rest_swagger-2.2.1.dist-info/RECORD
