Metadata-Version: 2.1
Name: mma-django-rest-swagger
Version: 2.2.1
Summary: Swagger UI for Django REST Framework 3.5+
Home-page: https://github.com/marcgibbons/django-rest-swagger
Author: Marc Gibbons
Author-email: marc_gibbons@rogers.com
License: FreeBSD License
Platform: UNKNOWN
Classifier: Environment :: Web Environment
Classifier: Framework :: Django
Classifier: Framework :: Django :: 1.8
Classifier: Framework :: Django :: 1.9
Classifier: Framework :: Django :: 1.10
Classifier: Framework :: Django :: 1.11
Classifier: Framework :: Django :: 2.0
Classifier: Framework :: Django :: 2.1
Classifier: Intended Audience :: Developers
Classifier: License :: OSI Approved :: BSD License
Classifier: Operating System :: OS Independent
Classifier: Programming Language :: Python
Classifier: Programming Language :: Python :: 2
Classifier: Programming Language :: Python :: 3
Classifier: Programming Language :: Python :: 2.7
Classifier: Programming Language :: Python :: 3.5
Classifier: Programming Language :: Python :: 3.6
Classifier: Topic :: Internet :: WWW/HTTP
Classifier: Topic :: Internet :: WWW/HTTP :: Dynamic Content
Requires-Dist: coreapi (>=2.3.0)
Requires-Dist: openapi-codec (>=1.3.1)
Requires-Dist: djangorestframework (>=3.5.4)
Requires-Dist: Django (>=1.8)
Requires-Dist: simplejson
